face_ai_kit/FaceRecognition.py
face_ai_kit/__init__.py
face_ai_kit/common/__init__.py
face_ai_kit/common/utils.py
face_ai_kit/config/base.yaml
face_ai_kit/core/__init__.py
face_ai_kit/core/align_trans.py
face_ai_kit/core/embedding_metrics.py
face_ai_kit/core/matlab_cp2tform.py
face_ai_kit/core/timer.py
face_ai_kit/core/transforms.py
face_ai_kit/modules/__init__.py
face_ai_kit/modules/mediapipe_landmarks/MediapipeLandmarks.py
face_ai_kit/modules/mediapipe_landmarks/MediapipeLandmarksFactory.py
face_ai_kit/modules/mediapipe_landmarks/__init__.py
face_ai_kit/modules/mediapipe_landmarks/inference/MediapipeLandmarksOnnx.py
face_ai_kit/modules/mediapipe_landmarks/inference/__init__.py
face_ai_kit/modules/n19_landmarks/N19Landmarks.py
face_ai_kit/modules/n19_landmarks/N19LandmarksFactory.py
face_ai_kit/modules/n19_landmarks/__init__.py
face_ai_kit/modules/n19_landmarks/inference/KeypointsOnnx.py
face_ai_kit/modules/n19_landmarks/inference/__init__.py
face_ai_kit/modules/n19_rotation/N19Rotation.py
face_ai_kit/modules/n19_rotation/__init__.py
face_ai_kit/modules/recognition/RecognitionFactory.py
face_ai_kit/modules/recognition/__init__.py
face_ai_kit/modules/recognition/arcface/ArcFace.py
face_ai_kit/modules/recognition/arcface/__init__.py
face_ai_kit/modules/recognition/arcface/inference/ArcFaceOnnx.py
face_ai_kit/modules/recognition/arcface/inference/ArcFaceRknn3568.py
face_ai_kit/modules/recognition/arcface/inference/ArcFaceRknn3588.py
face_ai_kit/modules/recognition/arcface/inference/__init__.py
face_ai_kit/modules/recognition/magface/MagFace.py
face_ai_kit/modules/recognition/magface/__init__.py
face_ai_kit/modules/recognition/magface/inference/MagFaceOnnx.py
face_ai_kit/modules/recognition/magface/inference/__init__.py
face_ai_kit/modules/recognition/magface_cwh/MagFaceCWH.py
face_ai_kit/modules/recognition/magface_cwh/__init__.py
face_ai_kit/modules/recognition/magface_cwh/inference/MagFaceCWHOnnx.py
face_ai_kit/modules/recognition/magface_cwh/inference/__init__.py
face_ai_kit-0.1.3.dist-info/LICENSE
face_ai_kit-0.1.3.dist-info/METADATA
face_ai_kit-0.1.3.dist-info/WHEEL
face_ai_kit-0.1.3.dist-info/top_level.txt
face_ai_kit-0.1.3.dist-info/RECORD
