Metadata-Version: 2.1
Name: face-ai-kit
Version: 0.1.3
Summary: FaceAIKit is a Python library designed for face detection and recognition application.
Home-page: 
Author: Tomas Goldmann
Author-email: igoldmann@fit.vutbr.cz
License: MIT
Classifier: Intended Audience :: Developers
Classifier: License :: OSI Approved :: MIT License
Classifier: Programming Language :: Python
Classifier: Programming Language :: Python :: 3.8
Classifier: Programming Language :: Python :: 3.9
Classifier: Programming Language :: Python :: 3.10
Classifier: Programming Language :: Python :: 3.11
Classifier: Operating System :: OS Independent
License-File: LICENSE
Requires-Dist: numpy
Requires-Dist: opencv-python
Requires-Dist: onnxruntime
Requires-Dist: gdown
Requires-Dist: confuse
Requires-Dist: scikit-image
